{"image_pair_names": ["REF_sin_nada_PB_con_todo", "REF_sin_nada_PB_sin_negativo", "REF_sin_nada_PB_sin_positivo", "REF_con_todo_PB_sin_negativo", "REF_con_todo_PB_sin_positivo", "REF_sin_negativo_PB_sin_positivo", "REF_0_2_PB_90"], "predicted_delta_phiCRs": {"Embedder_KNN_UMAP_Trained_wnon_noisy_DS_Exper": {"REF_sin_nada_PB_con_todo": -0.11387005094877356, "REF_sin_nada_PB_sin_negativo": -0.31755074554597496, "REF_sin_nada_PB_sin_positivo": 0.29491931572434926, "REF_con_todo_PB_sin_negativo": -0.2004881210710936, "REF_con_todo_PB_sin_positivo": 0.40878079317175575, "REF_sin_negativo_PB_sin_positivo": 0.6074912900857947, "REF_0_2_PB_90": -3.118277842329637}}, "times": {"Embedder_KNN_UMAP_Trained_wnon_noisy_DS_Exper": {"REF_sin_nada_PB_con_todo": 3.333179201398577, "REF_sin_nada_PB_sin_negativo": 3.333179201398577, "REF_sin_nada_PB_sin_positivo": 3.333179201398577, "REF_con_todo_PB_sin_negativo": 3.333179201398577, "REF_con_todo_PB_sin_positivo": 3.333179201398577, "REF_sin_negativo_PB_sin_positivo": 3.333179201398577, "REF_0_2_PB_90": 3.333179201398577}}}