{"image_pair_names": ["REF_sin_ninguno_PB_Con_los_dos", "REF_sin_ninguno_PB_sin_negativo", "REF_sin_ninguno_PB_Sin_positivo", "REF_Con_los_dos_PB_sin_negativo", "REF_Con_los_dos_PB_Sin_positivo", "REF_sin_negativo_PB_Sin_positivo"], "predicted_delta_phiCRs": {"Rot_Kalkandjiev_Fibo_Cubic_Interp_Exper_Sigm_k35_c0.7_iX": {"REF_sin_ninguno_PB_Con_los_dos": -0.35464877826499985, "REF_sin_ninguno_PB_sin_negativo": -0.24197564930249982, "REF_sin_ninguno_PB_Sin_positivo": -0.8911373157904998, "REF_Con_los_dos_PB_sin_negativo": 0.11267312896250004, "REF_Con_los_dos_PB_Sin_positivo": -0.5364885375255, "REF_sin_negativo_PB_Sin_positivo": -0.649161666488}, "Rot_Kalkandjiev_Quad_Cubic_Interp_Exper_Sigm_k35_c0.7_iX": {"REF_sin_ninguno_PB_Con_los_dos": -0.3546059115, "REF_sin_ninguno_PB_sin_negativo": -0.5035217445, "REF_sin_ninguno_PB_Sin_positivo": -0.8837263189999998, "REF_Con_los_dos_PB_sin_negativo": -0.148915833, "REF_Con_los_dos_PB_Sin_positivo": -0.5291204074999998, "REF_sin_negativo_PB_Sin_positivo": -0.3802045744999998}, "Rot_Kalkandjiev_Fibo_Lanc_Interp_Exper_Sigm_k35_c0.7_iX": {"REF_sin_ninguno_PB_Con_los_dos": -0.35470416437950014, "REF_sin_ninguno_PB_sin_negativo": -0.24220233537949998, "REF_sin_ninguno_PB_Sin_positivo": -0.8856761567810001, "REF_Con_los_dos_PB_sin_negativo": 0.11250182900000016, "REF_Con_los_dos_PB_Sin_positivo": -0.5309719924015, "REF_sin_negativo_PB_Sin_positivo": -0.6434738214015001}, "Rot_Kalkandjiev_Quad_Lanc_Interp_Exper_Sigm_k35_c0.7_iX": {"REF_sin_ninguno_PB_Con_los_dos": -0.35460512435000013, "REF_sin_ninguno_PB_sin_negativo": -0.503692247, "REF_sin_ninguno_PB_Sin_positivo": -0.88417453395, "REF_Con_los_dos_PB_sin_negativo": -0.1490871226499999, "REF_Con_los_dos_PB_Sin_positivo": -0.5295694095999999, "REF_sin_negativo_PB_Sin_positivo": -0.38048228694999997}, "Mir_Fibo_Cubic_Interp_Exper_Sigm_k35_c0.7_iX": {"REF_sin_ninguno_PB_Con_los_dos": -0.354852946746, "REF_sin_ninguno_PB_sin_negativo": -0.50377021937, "REF_sin_ninguno_PB_Sin_positivo": -0.8835511890800001, "REF_Con_los_dos_PB_sin_negativo": -0.148917272624, "REF_Con_los_dos_PB_Sin_positivo": -0.5286982423340001, "REF_sin_negativo_PB_Sin_positivo": -0.3797809697100001}, "Mir_Quad_Cubic_Interp_Exper_Sigm_k35_c0.7_iX": {"REF_sin_ninguno_PB_Con_los_dos": -0.35483437399999995, "REF_sin_ninguno_PB_sin_negativo": -0.5038668897, "REF_sin_ninguno_PB_Sin_positivo": -0.8876443341, "REF_Con_los_dos_PB_sin_negativo": -0.1490325157000001, "REF_Con_los_dos_PB_Sin_positivo": -0.5328099601, "REF_sin_negativo_PB_Sin_positivo": -0.38377744439999995}, "Mir_Fibo_Lanc_Interp_Exper_Sigm_k35_c0.7_iX": {"REF_sin_ninguno_PB_Con_los_dos": -0.35482782733000007, "REF_sin_ninguno_PB_sin_negativo": -0.5037703689019999, "REF_sin_ninguno_PB_Sin_positivo": -0.883550997912, "REF_Con_los_dos_PB_sin_negativo": -0.14894254157199982, "REF_Con_los_dos_PB_Sin_positivo": -0.5287231705819999, "REF_sin_negativo_PB_Sin_positivo": -0.3797806290100001}, "Mir_Quad_Lanc_Interp_Exper_Sigm_k35_c0.7_iX": {"REF_sin_ninguno_PB_Con_los_dos": -0.35483337970000006, "REF_sin_ninguno_PB_sin_negativo": -0.5039000885, "REF_sin_ninguno_PB_Sin_positivo": -0.8858364392, "REF_Con_los_dos_PB_sin_negativo": -0.14906670879999995, "REF_Con_los_dos_PB_Sin_positivo": -0.5310030594999999, "REF_sin_negativo_PB_Sin_positivo": -0.3819363507}, "Rot_Naive_Fibo_Cubic_Interp_Exper_Sigm_k35_c0.7_iX": {"REF_sin_ninguno_PB_Con_los_dos": -0.058766185612999955, "REF_sin_ninguno_PB_sin_negativo": -0.6105489023999997, "REF_sin_ninguno_PB_Sin_positivo": 0.5800775775640004, "REF_Con_los_dos_PB_sin_negativo": -0.07157681311400044, "REF_Con_los_dos_PB_Sin_positivo": 0.7529766205300001, "REF_sin_negativo_PB_Sin_positivo": 1.2122748285}, "Rot_Naive_Quad_Cubic_Interp_Exper_Sigm_k35_c0.7_iX": {"REF_sin_ninguno_PB_Con_los_dos": -0.05721985200000024, "REF_sin_ninguno_PB_sin_negativo": -0.6108021772000001, "REF_sin_ninguno_PB_Sin_positivo": 0.5801134240000003, "REF_Con_los_dos_PB_sin_negativo": -0.06740547303, "REF_Con_los_dos_PB_Sin_positivo": 1.1566061120000004, "REF_sin_negativo_PB_Sin_positivo": 1.2097956380000001}, "Rot_Naive_Fibo_Lanc_Interp_Exper_Sigm_k35_c0.7_iX": {"REF_sin_ninguno_PB_Con_los_dos": -0.05876609778600006, "REF_sin_ninguno_PB_sin_negativo": -0.6094017197969999, "REF_sin_ninguno_PB_Sin_positivo": 0.5800530461770004, "REF_Con_los_dos_PB_sin_negativo": -0.07157681311400044, "REF_Con_los_dos_PB_Sin_positivo": 0.7522977366000001, "REF_sin_negativo_PB_Sin_positivo": 1.0002459284079999}, "Rot_Naive_Quad_Lanc_Interp_Exper_Sigm_k35_c0.7_iX": {"REF_sin_ninguno_PB_Con_los_dos": -0.058733748999999946, "REF_sin_ninguno_PB_sin_negativo": -0.6133850723999998, "REF_sin_ninguno_PB_Sin_positivo": 0.5801570549999999, "REF_Con_los_dos_PB_sin_negativo": -0.07198405699999988, "REF_Con_los_dos_PB_Sin_positivo": 1.148278147, "REF_sin_negativo_PB_Sin_positivo": -1.9519253057999997}, "Rel_Rot_Fourier_Phase_Correlat_Exper_Sigm_k35_c0.7_iX": {"REF_sin_ninguno_PB_Con_los_dos": -0.22043508452688343, "REF_sin_ninguno_PB_sin_negativo": -0.4740314248416597, "REF_sin_ninguno_PB_Sin_positivo": 0.5485569839018178, "REF_Con_los_dos_PB_sin_negativo": -0.16580627893946165, "REF_Con_los_dos_PB_Sin_positivo": 0.959058423970884, "REF_sin_negativo_PB_Sin_positivo": 1.094845039776043}, "Histo_Intra_Class_Var_Exper_Sigm_k35_c0.7_iX": {"REF_sin_ninguno_PB_Con_los_dos": -0.13943507120042398, "REF_sin_ninguno_PB_sin_negativo": -0.3890410628555028, "REF_sin_ninguno_PB_Sin_positivo": 0.3769911184307751, "REF_Con_los_dos_PB_sin_negativo": -0.24960599165507968, "REF_Con_los_dos_PB_Sin_positivo": 0.5164261896311988, "REF_sin_negativo_PB_Sin_positivo": 0.7660321812862783}, "Grad_Regress_Exper_Sigm_k35_c0.7_iX": {"REF_sin_ninguno_PB_Con_los_dos": -0.5961579993267376, "REF_sin_ninguno_PB_sin_negativo": -0.424790884335823, "REF_sin_ninguno_PB_Sin_positivo": 0.7089377916481068, "REF_Con_los_dos_PB_sin_negativo": 0.17136711499091462, "REF_Con_los_dos_PB_Sin_positivo": 1.3050957909748444, "REF_sin_negativo_PB_Sin_positivo": 1.1337286759839298}}, "times": {"Rot_Kalkandjiev_Fibo_Cubic_Interp_Exper_Sigm_k35_c0.7_iX": {"REF_sin_ninguno_PB_Con_los_dos": 0.36, "REF_sin_ninguno_PB_sin_negativo": 0.35, "REF_sin_ninguno_PB_Sin_positivo": 0.4, "REF_Con_los_dos_PB_sin_negativo": 0.42000000000000004, "REF_Con_los_dos_PB_Sin_positivo": 0.47, "REF_sin_negativo_PB_Sin_positivo": 0.36}, "Rot_Kalkandjiev_Quad_Cubic_Interp_Exper_Sigm_k35_c0.7_iX": {"REF_sin_ninguno_PB_Con_los_dos": 0.24000000000000002, "REF_sin_ninguno_PB_sin_negativo": 0.22999999999999998, "REF_sin_ninguno_PB_Sin_positivo": 0.24, "REF_Con_los_dos_PB_sin_negativo": 0.24, "REF_Con_los_dos_PB_Sin_positivo": 0.25, "REF_sin_negativo_PB_Sin_positivo": 0.27}, "Rot_Kalkandjiev_Fibo_Lanc_Interp_Exper_Sigm_k35_c0.7_iX": {"REF_sin_ninguno_PB_Con_los_dos": 0.63, "REF_sin_ninguno_PB_sin_negativo": 0.5, "REF_sin_ninguno_PB_Sin_positivo": 0.59, "REF_Con_los_dos_PB_sin_negativo": 0.56, "REF_Con_los_dos_PB_Sin_positivo": 0.7, "REF_sin_negativo_PB_Sin_positivo": 0.5}, "Rot_Kalkandjiev_Quad_Lanc_Interp_Exper_Sigm_k35_c0.7_iX": {"REF_sin_ninguno_PB_Con_los_dos": 0.42000000000000004, "REF_sin_ninguno_PB_sin_negativo": 0.43, "REF_sin_ninguno_PB_Sin_positivo": 0.43, "REF_Con_los_dos_PB_sin_negativo": 0.38, "REF_Con_los_dos_PB_Sin_positivo": 0.4, "REF_sin_negativo_PB_Sin_positivo": 0.42000000000000004}, "Mir_Fibo_Cubic_Interp_Exper_Sigm_k35_c0.7_iX": {"REF_sin_ninguno_PB_Con_los_dos": 0.41000000000000003, "REF_sin_ninguno_PB_sin_negativo": 0.32, "REF_sin_ninguno_PB_Sin_positivo": 0.35, "REF_Con_los_dos_PB_sin_negativo": 0.4, "REF_Con_los_dos_PB_Sin_positivo": 0.41000000000000003, "REF_sin_negativo_PB_Sin_positivo": 0.37}, "Mir_Quad_Cubic_Interp_Exper_Sigm_k35_c0.7_iX": {"REF_sin_ninguno_PB_Con_los_dos": 0.214, "REF_sin_ninguno_PB_sin_negativo": 0.22999999999999998, "REF_sin_ninguno_PB_Sin_positivo": 0.28, "REF_Con_los_dos_PB_sin_negativo": 0.21000000000000002, "REF_Con_los_dos_PB_Sin_positivo": 0.28700000000000003, "REF_sin_negativo_PB_Sin_positivo": 0.259}, "Mir_Fibo_Lanc_Interp_Exper_Sigm_k35_c0.7_iX": {"REF_sin_ninguno_PB_Con_los_dos": 0.64, "REF_sin_ninguno_PB_sin_negativo": 0.56, "REF_sin_ninguno_PB_Sin_positivo": 0.5900000000000001, "REF_Con_los_dos_PB_sin_negativo": 0.54, "REF_Con_los_dos_PB_Sin_positivo": 0.6100000000000001, "REF_sin_negativo_PB_Sin_positivo": 0.68}, "Mir_Quad_Lanc_Interp_Exper_Sigm_k35_c0.7_iX": {"REF_sin_ninguno_PB_Con_los_dos": 0.41000000000000003, "REF_sin_ninguno_PB_sin_negativo": 0.39, "REF_sin_ninguno_PB_Sin_positivo": 0.36, "REF_Con_los_dos_PB_sin_negativo": 0.36, "REF_Con_los_dos_PB_Sin_positivo": 0.36, "REF_sin_negativo_PB_Sin_positivo": 0.37}, "Rot_Naive_Fibo_Cubic_Interp_Exper_Sigm_k35_c0.7_iX": {"REF_sin_ninguno_PB_Con_los_dos": 0.19, "REF_sin_ninguno_PB_sin_negativo": 0.17, "REF_sin_ninguno_PB_Sin_positivo": 0.17, "REF_Con_los_dos_PB_sin_negativo": 0.19, "REF_Con_los_dos_PB_Sin_positivo": 0.18, "REF_sin_negativo_PB_Sin_positivo": 0.16}, "Rot_Naive_Quad_Cubic_Interp_Exper_Sigm_k35_c0.7_iX": {"REF_sin_ninguno_PB_Con_los_dos": 0.14, "REF_sin_ninguno_PB_sin_negativo": 0.16, "REF_sin_ninguno_PB_Sin_positivo": 0.13, "REF_Con_los_dos_PB_sin_negativo": 0.13, "REF_Con_los_dos_PB_Sin_positivo": 0.14, "REF_sin_negativo_PB_Sin_positivo": 0.13}, "Rot_Naive_Fibo_Lanc_Interp_Exper_Sigm_k35_c0.7_iX": {"REF_sin_ninguno_PB_Con_los_dos": 0.33, "REF_sin_ninguno_PB_sin_negativo": 0.3, "REF_sin_ninguno_PB_Sin_positivo": 0.27, "REF_Con_los_dos_PB_sin_negativo": 0.29, "REF_Con_los_dos_PB_Sin_positivo": 0.28, "REF_sin_negativo_PB_Sin_positivo": 0.37}, "Rot_Naive_Quad_Lanc_Interp_Exper_Sigm_k35_c0.7_iX": {"REF_sin_ninguno_PB_Con_los_dos": 0.18, "REF_sin_ninguno_PB_sin_negativo": 0.23, "REF_sin_ninguno_PB_Sin_positivo": 0.18, "REF_Con_los_dos_PB_sin_negativo": 0.25, "REF_Con_los_dos_PB_Sin_positivo": 0.19, "REF_sin_negativo_PB_Sin_positivo": 0.23}, "Rel_Rot_Fourier_Phase_Correlat_Exper_Sigm_k35_c0.7_iX": {"REF_sin_ninguno_PB_Con_los_dos": 0.24246954917907715, "REF_sin_ninguno_PB_sin_negativo": 0.25066280364990234, "REF_sin_ninguno_PB_Sin_positivo": 0.2885129451751709, "REF_Con_los_dos_PB_sin_negativo": 0.26133298873901367, "REF_Con_los_dos_PB_Sin_positivo": 0.25853514671325684, "REF_sin_negativo_PB_Sin_positivo": 0.28531575202941895}, "Histo_Intra_Class_Var_Exper_Sigm_k35_c0.7_iX": {"REF_sin_ninguno_PB_Con_los_dos": 0.15406394004821777, "REF_sin_ninguno_PB_sin_negativo": 0.14483356475830078, "REF_sin_ninguno_PB_Sin_positivo": 0.14138150215148926, "REF_Con_los_dos_PB_sin_negativo": 0.1395423412322998, "REF_Con_los_dos_PB_Sin_positivo": 0.1595613956451416, "REF_sin_negativo_PB_Sin_positivo": 0.14356350898742676}, "Grad_Regress_Exper_Sigm_k35_c0.7_iX": {"REF_sin_ninguno_PB_Con_los_dos": 1.44270658493042, "REF_sin_ninguno_PB_sin_negativo": 1.455552577972412, "REF_sin_ninguno_PB_Sin_positivo": 1.5407462120056152, "REF_Con_los_dos_PB_sin_negativo": 1.4295463562011719, "REF_Con_los_dos_PB_Sin_positivo": 1.4390921592712402, "REF_sin_negativo_PB_Sin_positivo": 1.4848144054412842}}}